{
  "title": "보르쿠타 - 베츄아 강 철교",
  "id": "6333271",
  "index": 16,
  "contents": [
    {
      "textJP": "ベチュア河鉄橋に発進",
      "textKO": "베츄아 강 철교로 발진"
    },
    {
      "text": ""
    },
    {
      "scriptJP": "ブレンダ：この場所を越えると反政府軍の拠点があるそうよ。",
      "scriptKO": "브렌다 : 이곳을 넘으면 반 정부군의 거점이 있다고 해."
    },
    {
      "scriptJP": "アルベルト：そうか・・・。じゃあ、そこでツェルネンコの情報を仕入れよう。",
      "scriptKO": "알베르트 : 그런가... 그럼, 그곳에서 체르넨코의 정보도 들어오겠군."
    },
    {
      "scriptJP": "ブレンダ：それにしても・・・あのヨハンセンって男。",
      "scriptKO": "브렌다 : 그건 그렇고... 요한센이라는 남자."
    },
    {
      "scriptJP": "どうも信用出来ないわ。",
      "scriptKO": "아무래도 신용할 수 없어."
    },
    {
      "scriptJP": "アルベルト：まあな、でもこれも仕事だろ？",
      "scriptKO": "알베르트 : 그건 그래, 하지만 이것도 일이잖아?"
    },
    {
      "scriptJP": "ブレンダ：そ、そうだったわね・・・あれ？",
      "scriptKO": "브렌다 : 그, 그랬었지... 응?"
    },
    {
      "scriptJP": "アルベルト：どうした？",
      "scriptKO": "알베르트 : 무슨 일이야?"
    },
    {
      "scriptJP": "ブレンダ：地上に味方機の反応があるわ。",
      "scriptKO": "브렌다 : 지상에 아군기 반응이 있어."
    },
    {
      "scriptJP": "一機だけみたいだけど。",
      "scriptKO": "1 기뿐이지만."
    },
    {
      "scriptJP": "アルベルト：可笑しいな、こんなところで一機だけとは",
      "scriptKO": "알베르트 : 이상하군, 이런 곳에서 1기뿐이라니"
    },
    {
      "scriptJP": "降りて調べてくる。",
      "scriptKO": "내려서 확인해 볼게"
    },
    {
      "scriptJP": "ブレンダ：ちょっとちょっと・・・",
      "scriptKO": "브렌다 : 자, 잠깐..."
    },
    {
      "scriptJP": "ブレンダ：全く物好きね・・・",
      "scriptKO": "브렌다 : 참내 별난 사람이야..."
    },
    {
      "scriptJP": "ブレンダ：こんな寒い所にいると心まで冷えそうだわ",
      "scriptKO": "브렌다 : 이렇게 추운 곳에 있으면 마음까지 차가워 질것 같아."
    },
    {
      "text": ""
    },
    {
      "textJP": "ベチュア河鉄橋",
      "textKO": "베츄아 강 철교"
    },
    {
      "text": ""
    },
    {
      "scriptJP": "アルベルト：お前も反政府軍の兵だな？",
      "scriptKO": "알베르트 : 너도 반 정부군의 병사지?"
    },
    {
      "scriptJP": "どうしたんだ？　ここで何をしている。",
      "scriptKO": "무슨 일이야? 여기서 무엇을 하고 있는 거야"
    },
    {
      "scriptJP": "エミル：ううっ・・・",
      "scriptKO": "에밀 : 으윽..."
    },
    {
      "scriptJP": "味方の部隊が全滅したんです・・・",
      "scriptKO": "아군 부대가 전멸했어요"
    },
    {
      "scriptJP": "僕のヴァンツァーは補給機だったから後方にいて・・・",
      "scriptKO": "내 번쳐는 보급기라 후방에 있어서..."
    },
    {
      "scriptJP": "それで逃げてこられたんだけど・・・",
      "scriptKO": "그래서 도망칠 수 있었지만..."
    },
    {
      "scriptJP": "アルベルト：早く基地に戻った方がいいぞ。",
      "scriptKO": "알베르트 : 어서 기지로 돌아가는 게 좋아."
    },
    {
      "scriptJP": "この辺りはまだ危険だ。",
      "scriptKO": "이 주변은 아직 위험해."
    },
    {
      "scriptJP": "エミル：でも・・・同志ヨハンセンは",
      "scriptKO": "에밀 : 하지만... 동지 요한센은"
    },
    {
      "scriptJP": "厳しい人だから・・・",
      "scriptKO": "엄격한 사람이라..."
    },
    {
      "scriptJP": "僕一人だけが生き残った事を知ったら・・",
      "scriptKO": "나 혼자만 살아남은 것을 알면..."
    },
    {
      "scriptJP": "アルベルト：・・・・・・",
      "scriptKO": "알베르트 : ......"
    },
    {
      "scriptJP": "エミル：彼は任務に失敗した部下を許さないんです。",
      "scriptKO": "에밀 : 그는 임무에 실패한 부하는 용서하지 않아요."
    },
    {
      "scriptJP": "アルベルト：しかし、ここにいたからってどうなるものでもないだろう？",
      "scriptKO": "알베르트 : 하지만, 이곳에 있는다고 해서 어떻게 되는 것도 아니잖아?"
    },
    {
      "scriptJP": "ぐずぐずしていると政府軍に見つかってしまうぞ！",
      "scriptKO": "꾸물대다간 정부군에 발각될 거야!"
    },
    {
      "scriptJP": "ブレンダ：もう遅いわよ！",
      "scriptKO": "브렌다 : 이미 늦었어!"
    },
    {
      "scriptJP": "敵のヴァンツァー隊がそっちに向かってる！",
      "scriptKO": "적의 번쳐부대가 그쪽을 향하고 있어!"
    },
    {
      "scriptJP": "アルベルト：ちっ！まずいな。",
      "scriptKO": "알베르트 : 쳇! 좋지 않군."
    },
    {
      "scriptJP": "早くヴァンツァーに乗り込め！",
      "scriptKO": "서둘러 번쳐에 탑승해!"
    },
    {
      "scriptJP": "エミル：わ、分かりました。",
      "scriptKO": "에밀 : 아, 알겠어요."
    },
    {
      "scriptJP": "アルベルト：敵はかなり手強そうだ。",
      "scriptKO": "알베르트 : 적은 상당히 강한 것 같아"
    },
    {
      "scriptJP": "お前はすきを見て基地へ急げ！",
      "scriptKO": "너도 틈을 봐서 기지로 서둘러!"
    },
    {
      "scriptJP": "エミル：いや、僕も一緒に戦います。",
      "scriptKO": "에밀 : 아니에요 나도 함께 싸울래요."
    },
    {
      "scriptJP": "僕のヴァンツァーならあなたの機体を回復させられるから。",
      "scriptKO": "내 번쳐라면 당신의 기체를 회복시킬 수 있으니까요."
    },
    {
      "scriptJP": "エミル：それに僕は戦いの中で死んだ方がいいんだ。",
      "scriptKO": "에밀 : 게다가 나는 전투에서 죽는 편이 나아."
    },
    {
      "scriptJP": "それが革命のためなんだ。",
      "scriptKO": "그게 혁명을 위해서야."
    },
    {
      "scriptJP": "アルベルト：・・・・・・わかった。",
      "scriptKO": "알베르트 : ...... 알았어."
    },
    {
      "scriptJP": "その代わり、生き残ったら基地へ戻るんだぞ！",
      "scriptKO": "그 대신, 살아남으면 기지로 돌아가는 거야!"
    },
    {
      "scriptJP": "エミル：えっ！？は、はい・・・",
      "scriptKO": "에밀 : 에!? 예, 예..."
    },
    {
      "text": ""
    },
    {
      "scriptJP": "アルベルト：ふう。何とか追い払えたようだぞ。",
      "scriptKO": "알베르트 : 후우. 어떻게든 쫓아낸 것 같군."
    },
    {
      "scriptJP": "エミル：ありごとうございます。こんな僕のために・・・",
      "scriptKO": "에밀 : 감사합니다. 이런 나를 위해..."
    },
    {
      "scriptJP": "僕の名前はエミル・シンスキー",
      "scriptKO": "내 이름은 에밀 신스키"
    },
    {
      "scriptJP": "反政府軍ヴァンツァー部隊の補給機のパイロットです。",
      "scriptKO": "반 정부군 번쳐 부대의 보급기 파일럿이에요."
    },
    {
      "scriptJP": "エミル：でも僕の部隊は全滅してしまいましたが・・・",
      "scriptKO": "에밀 : 하지만 내 부대는 전멸해 버렸지만..."
    },
    {
      "scriptJP": "アルベルト：そんなに気を落とすな。",
      "scriptKO": "알베르트 : 그렇게 낙심하지 마."
    },
    {
      "scriptJP": "俺との約束は覚えているよな？",
      "scriptKO": "나와의 약속은 기억하고 있지?"
    },
    {
      "scriptJP": "エミル：・・・はい。",
      "scriptKO": "에밀 : ... 네."
    },
    {
      "scriptJP": "基地に帰って同志ヨハンセンに説明してみるつもりです。",
      "scriptKO": "기지에 돌아가서 동지 요한센에게 설명해 볼 생각이에요."
    },
    {
      "scriptJP": "アルベルト：それでいい。",
      "scriptKO": "알베르트 : 그걸로 됐어."
    },
    {
      "scriptJP": "実は俺もこれから基地へ行くつもりなんだ。",
      "scriptKO": "실은 나도 이제부터 기지로 갈 생각이야."
    },
    {
      "scriptJP": "エミル：そうですか。また会えるといいですね。",
      "scriptKO": "에밀 : 그래요? 또 만날 수 있으면 좋겠네요."
    },
    {
      "scriptJP": "じゃあ、お先に。",
      "scriptKO": "그럼, 먼저 갈게요."
    },
    {
      "text": ""
    },
    {
      "scriptJP": "ブレンダ：彼はどうしたの？",
      "scriptKO": "브렌다 : 그는 어디 있어?"
    },
    {
      "scriptJP": "アルベルト：自分のヴァンツァーで基地へ帰ったはずだ。",
      "scriptKO": "알베르트 : 자기 번쳐를 타고 기지로 돌아갔을 거야."
    },
    {
      "scriptJP": "俺達も行ってみよう。",
      "scriptKO": "우리도 가보자."
    },
    {
      "text": ""
    },
    {
      "textJP": "ボルクタ",
      "textKO": "보르쿠타"
    },
    {
      "text": ""
    },
    {
      "scriptJP": "ブレンダ：反政府軍の基地はここから遠くないわ。",
      "scriptKO": "브렌다 : 반 정부군의 기지는 여기에서 멀지 않아."
    },
    {
      "text": ""
    },
    {
      "text": "[클라크를 동료로 얻지 않았을 때]"
    },
    {
      "text": ""
    },
    {
      "scriptJP": "アルベルト：しかし・・・反政府軍とは",
      "scriptKO": "알베르트 : 하지만... 반 정부군이란"
    },
    {
      "scriptJP": "それ程厳しい所なのか・・・",
      "scriptKO": "그렇게 혹독한 곳인 걸까..."
    },
    {
      "scriptJP": "ブレンダ：まあエミルのせいで隊が全滅した訳じゃないし、",
      "scriptKO": "브렌다 : 에이, 에밀 때문에 부대가 전멸한 것도 아니고,"
    },
    {
      "textextJPKO": "ヨハンセンも解かってくれるんじゃないかしら？",
      "scriptKO": "요한센도 알아주지 않을까?"
    },
    {
      "text": ""
    },
    {
      "text": "[클라크를 동료로 얻었을 때]"
    },
    {
      "text": ""
    },
    {
      "scriptJP": "クラーク：しかし・・・反政府軍とは",
      "scriptKO": "클라크 : 하지만... 반 정부군이란"
    },
    {
      "scriptJP": "それ程厳しい所なのでしょうか。",
      "scriptKO": "그렇게 지독한 곳인 겁니까?"
    },
    {
      "scriptJP": "同じ軍人としても理解できませんな。",
      "scriptKO": "같은 군인으로서도 이해할 수 없습니다."
    },
    {
      "scriptJP": "ブレンダ：ランドルフ少佐は優しそうだったものね",
      "scriptKO": "브렌다 : 랜돌프 소령도 다정해 보였었지."
    },
    {
      "scriptJP": "アルベルト：まあエミルのせいで隊が全滅した訳ではないし",
      "scriptKO": "알베르트 : 뭐, 에밀 때문에 부대가 전멸한 것도 아니고"
    },
    {
      "scriptJP": "ヨハンセンも解ってくれるだろう。",
      "scriptKO": "요한센도 알아주겠지."
    }
  ]
}
