{
  "title": "잔볼라 - 탄가니 의사당",
  "id": "6335995",
  "index": 40
  ,
  "contents": [
    {
      "textJP": "タンガニー議事堂に発進",
      "textKO": "탄가니 의사당으로 발진"
    },
    {
      "text": ""
    },
    {
      "scriptJP": "ブレンダ：和平会議会場よ。",
      "scriptKO": "브렌다 : 평화 회의 회장이야."
    },
    {
      "scriptJP": "首相、頑張って下さいね。",
      "scriptKO": "수상, 힘내십시오."
    },
    {
      "scriptJP": "エミル：アフリカの平和は首相に掛かっています。",
      "scriptKO": "에밀 : 아프리카의 평화는 수상에게 달려있어요."
    },
    {
      "text": ""
    },
    {
      "text": "[사카타를 동료로 얻었을 때]"
    },
    {
      "text": ""
    },
    {
      "scriptJP": "サカタ：わしも、応援させてもらうぞ。平和を願う者としてな。",
      "scriptKO": "사카타 : 나도 응원하겠어. 평화를 바라는 사람으로서 말이야."
    },
    {
      "text": ""
    },
    {
      "scriptJP": "アクセル：父ちゃんも、死んだ村の人達も、",
      "scriptKO": "엑셀 : 아버지도, 죽은 마을 사람들도,"
    },
    {
      "scriptJP": "首相を応援してるはずだよ。",
      "scriptKO": "수상을 응원하고 있을 겁니다."
    },
    {
      "scriptJP": "エルガー：皆、ありがとう。任せてくれたまえ。",
      "scriptKO": "엘거 : 모두, 고맙네. 맡겨 두게나."
    },
    {
      "text": ""
    },
    {
      "textJP": "タンガニー議事堂",
      "textKO": "탄가니 의사당"
    },
    {
      "text": ""
    },
    {
      "scriptJP": "アルベルト：いよいよだな。",
      "scriptKO": "알베르트 : 드디어인가."
    },
    {
      "scriptJP": "ブレンダ：この和平会議、何とか成功させなくちゃ。",
      "scriptKO": "브렌다 : 이 평화 회의, 어떻게든 성공시켜야만 해."
    },
    {
      "scriptJP": "アルベルト：周りの様子は？",
      "scriptKO": "알베르트 : 주변의 상황은?"
    },
    {
      "scriptJP": "ブレンダ：ええ、異常なしよ。",
      "scriptKO": "브렌다 : 응, 이상 없어."
    },
    {
      "scriptJP": "前方の首相達にも特に動きはないわ。",
      "scriptKO": "전방의 수상들에도 특별히 움직임은 없어."
    },
    {
      "scriptJP": "アルベルト：よし、俺も首相の方に向かう。",
      "scriptKO": "알베르트 : 좋아, 나도 수상에게로 향할 게."
    },
    {
      "text": ""
    },
    {
      "scriptJP": "アルベルト：首相、回りに怪しい動きはありませんでした。",
      "scriptKO": "알베르트 : 수상 각하, 주변에 수상한 움직임은 없었습니다."
    },
    {
      "scriptJP": "しかし、油断しないでください。",
      "scriptKO": "하지만, 방심하지 말아 주십시오."
    },
    {
      "scriptJP": "エルガー：ああ、しかしこの和平案さえ決まれば、戦争も終わる。",
      "scriptKO": "엘거 : 아아, 하지만 이 평화안만 결정되면 전쟁도 끝날 걸세."
    },
    {
      "scriptJP": "どんな連中もムチャは出来なくなるだろう。",
      "scriptKO": "그 어떤 녀석들도 난폭한 짓을 할 수는 없겠지."
    },
    {
      "scriptJP": "キール：首相！！覚悟してもらおう！",
      "scriptKO": "킬 : 수상!! 각오해라!"
    },
    {
      "scriptJP": "エルガー：キール君！！",
      "scriptKO": "엘거 : 킬 군!!"
    },
    {
      "scriptJP": "な、何をするっ！",
      "scriptKO": "무, 무슨 짓을!"
    },
    {
      "scriptJP": "キール：エルガー首相！",
      "scriptKO": "킬 : 엘거 수상!"
    },
    {
      "scriptJP": "この会議を成功させる訳にはいかんのです。",
      "scriptKO": "이 회의를 성공시킬 수는 없습니다."
    },
    {
      "scriptJP": "アルベルト：何だって！？",
      "scriptKO": "알베르트 : 뭐라고!?"
    },
    {
      "scriptJP": "そうか・・・貴様がスパイだったのか！",
      "scriptKO": "그런가... 네 녀석이 스파이였구나!"
    },
    {
      "scriptJP": "キール：その通りだよ。",
      "scriptKO": "킬 : 그 말대로다."
    },
    {
      "scriptJP": "貴様らに、首相を探させ、その後で始末するつもりだったのだ。",
      "scriptKO": "네 녀석들이, 수상을 찾아내면, 그 뒤에 해치울 셈이었다."
    },
    {
      "scriptJP": "くそ・・・後少しでソサエティのメンバーになれたのに！",
      "scriptKO": "제길... 앞으로 조금이면 소사이어티의 멤버가 될 수 있었는데!"
    },
    {
      "scriptJP": "何故、生きて帰って来た！",
      "scriptKO": "어째서, 살아 돌아왔나!"
    },
    {
      "scriptJP": "アルベルト：ソサエティ！？",
      "scriptKO": "알베르트 : 소사이어티!?"
    },
    {
      "scriptJP": "エルガー：ソサエティだと？何の事だ。",
      "scriptKO": "엘거 : 소사이어티라고? 무슨 얘긴가.."
    },
    {
      "scriptJP": "自分の国を売る程大事な物だとでも言うのか！",
      "scriptKO": "자신의 나라를 팔 정도로 중요한 것이라는 건가!"
    },
    {
      "scriptJP": "キール：フフッ、お前などには解るまい。",
      "scriptKO": "킬 : 후훗, 너 따위에게는 이해할 수 없을걸."
    },
    {
      "scriptJP": "ソサエティの権力はこんな国など簡単に・・・",
      "scriptKO": "소사이어티의 권력은 이런 나라 따위 간단히..."
    },
    {
      "text": ""
    },
    {
      "scriptJP": "キール：ぐわあっ！",
      "scriptKO": "킬 : 으악!"
    },
    {
      "scriptJP": "バルミング：このおしゃべりが！もう我慢出来んわ！",
      "scriptKO": "발밍 : 이 수다쟁이가! 더 이상 참을 수 없다!"
    },
    {
      "scriptJP": "エルガー：その声はバルミング将軍！",
      "scriptKO": "엘거 : 그 목소리는 발밍 장군!"
    },
    {
      "scriptJP": "やはり今回の件は君が背後にいたのか！",
      "scriptKO": "역시 이번 일은 자네가 배후에 있었던 건가!"
    },
    {
      "scriptJP": "バルミング：そうとも。",
      "scriptKO": "발밍 : 그렇고말고."
    },
    {
      "scriptJP": "あんたが生きていると困る人達がいるんでな。",
      "scriptKO": "당신이 살아 있으면 곤란한 사람들이 있다."
    },
    {
      "scriptJP": "ここで死んで頂こう！",
      "scriptKO": "여기서 죽어줘야겠어!"
    },
    {
      "scriptJP": "アルベルト：やめろっ！",
      "scriptKO": "알베르트 : 그만둬!"
    },
    {
      "text": ""
    },
    {
      "scriptJP": "バルミング：くそ、厄介な！",
      "scriptKO": "발밍 : 제길, 성가시군!"
    },
    {
      "scriptJP": "よかろう、お前と首相、ここで纏めて始末してくれるわ！",
      "scriptKO": "좋아, 너와 수상 모두, 여기서 한꺼번에 해치워 주마!"
    },
    {
      "scriptJP": "アルベルト：将軍！",
      "scriptKO": "알베르트 : 장군!"
    },
    {
      "scriptJP": "ソサエティについて話してもらおうか。",
      "scriptKO": "소사이어티에 대해 이야기 해 볼까."
    },
    {
      "scriptJP": "バルミング：わしは・・何も知らん・・・",
      "scriptKO": "발밍 : 나는... 아무것도 몰라..."
    },
    {
      "scriptJP": "わしのような・・下級・・メンバーには・・・",
      "scriptKO": "나 같은... 하급... 멤버에게는..."
    },
    {
      "scriptJP": "殆ど何も・・・教えては、くれ・・ない・・",
      "scriptKO": "거의 아무것도... 가르쳐주진, 않아..."
    },
    {
      "scriptJP": "アルベルト：一国の元首が下級メンバーだと？",
      "scriptKO": "알베르트 : 한 나라의 원수가 하급 멤버라고?"
    },
    {
      "scriptJP": "バルミング：ぐははははは。",
      "scriptKO": "발밍 : 크하하하하하"
    },
    {
      "scriptJP": "命が惜しければ、あまり深入りせん事だな・・・",
      "scriptKO": "목숨이 아깝다면, 그다지 깊게 파고들지 않는 게 좋을 거야..."
    },
    {
      "scriptJP": "バルミング：では・・・さらば、地獄で待っている・・ぞ",
      "scriptKO": "발밍 : 그럼... 안녕이다, 지옥에서 기다리겠...다."
    },
    {
      "scriptJP": "アルベルト：何てことだ。",
      "scriptKO": "알베르트 : 어떻게 된 일이야."
    },
    {
      "scriptJP": "この国でもソサエティの狂気が・・・",
      "scriptKO": "이 나라에서도 소사이어티의 광기가..."
    },
    {
      "scriptJP": "エルガー：危ない所だった・・・",
      "scriptKO": "엘거 : 위험했네...."
    },
    {
      "scriptJP": "アルベルト君、また、君に助けられたな、本当にありがとう。",
      "scriptKO": "알베르트 군, 또다시, 자네에게 도움을 받았군. 정말로 고맙네."
    },
    {
      "scriptJP": "アルベルト：ええ、しかし和平会議が・・・",
      "scriptKO": "알베르트 : 아아, 하지만 평화 회의가....."
    },
    {
      "scriptJP": "エルガー：うむ。これでは会議どころではないが・・・",
      "scriptKO": "엘거 : 음. 이래서는 회의를 할 수가 없겠군..."
    },
    {
      "scriptJP": "アルベルト：くそっ、奴らめ！",
      "scriptKO": "알베르트 : 제길, 녀석들!"
    },
    {
      "scriptJP": "首相が、命がけでやって来たというのに・・・",
      "scriptKO": "수상이, 목숨을 걸고 왔는데..."
    },
    {
      "scriptJP": "エルガー：私は諦めんよ。",
      "scriptKO": "엘거 : 나는 포기하지 않을 걸세.."
    },
    {
      "scriptJP": "近い内に、また会議を開き必ず成功させてみせる。",
      "scriptKO": "빠른 시일 내에, 다시 회의를 열어, 반드시 성공시켜 보이겠네."
    },
    {
      "scriptJP": "アルベルト：首相・・・",
      "scriptKO": "알베르트 : 수상..."
    },
    {
      "scriptJP": "俺も応援します。頑張って下さい。",
      "scriptKO": "저도 응원합니다. 힘내십시오."
    },
    {
      "scriptJP": "エルガー：ありがとう。",
      "scriptKO": "엘거 : 고맙네."
    },
    {
      "text": ""
    },
    {
      "textJP": "タンガニー議事堂",
      "textKO": "탄가니 의사당"
    },
    {
      "text": ""
    },
    {
      "scriptJP": "エルガー：今回はこんなことになってしまったが、",
      "scriptKO": "엘거 : 이번에는 이렇게 돼버렸지만,"
    },
    {
      "scriptJP": "私はいずれ和平会議を成功させてみせるつもりだ。",
      "scriptKO": "나는 언젠가 평화 회의를 성공시켜 보일 생각이네."
    },
    {
      "text": ""
    },
    {
      "scriptJP": "士官：私はタンガニー新政府の特使です。",
      "scriptKO": "사관 : 저는 탄가니 신 정부의 특사입니다."
    },
    {
      "scriptJP": "バルミング将軍の悪事が表に出たために、我が国も変わりつつあります。",
      "scriptKO": "발밍 장군의 악행이 겉으로 드러났기 때문에 우리나라도 변하고 있습니다."
    },
    {
      "scriptJP": "きっと会議はうまくいきますよ。",
      "scriptKO": "분명 회의는 순조로울 것입니다."
    },
    {
      "text": ""
    },
    {
      "textJP": "ジャンガ村",
      "textKO": "장가 마을"
    },
    {
      "text": ""
    },
    {
      "scriptJP": "ボンゴ村長：村は我々生き残りのもん達で、立て直すよ。",
      "scriptKO": "봉고 촌장 : 마을은 우리들 살아남은 사람들이, 다시 세울 걸세."
    },
    {
      "scriptJP": "アクセルのことは頼みましたぞ。",
      "scriptKO": "엑셀을 잘 부탁한다네."
    },
    {
      "text": ""
    },
    {
      "textJP": "ザンボラ上空",
      "textKO": "잔볼라 상공"
    },
    {
      "text": ""
    },
    {
      "scriptJP": "アクセル：アルベルトさん、ありがとう。首相を救ってくれて。",
      "scriptKO": "엑셀 : 알베르트 씨, 고마워. 수상을 구해줘서."
    },
    {
      "scriptJP": "アルベルト：いや・・・",
      "scriptKO": "알베르트 : 아니..."
    },
    {
      "scriptJP": "君こそ、あのジェノスから首相を守りきったんだ、大したものだ。",
      "scriptKO": "자네야말로 그 제노스에게서 수상을 지켜냈어, 대단한 거야."
    },
    {
      "scriptJP": "アクセル：へへへ・・・まあな。",
      "scriptKO": "엑셀 : 헤헤헤.... 뭐 그거야."
    },
    {
      "scriptJP": "おいらは２年前までアフリカの統一平和維持軍にいたんだ。",
      "scriptKO": "나는 2년 전까지 아프리카의 통일 평화 유지 군이었어."
    },
    {
      "scriptJP": "ヴァンツァーの腕ではおいらに敵う奴ぁいなかったね。",
      "scriptKO": "번쳐 조종 실력은 나에게 대적할 사람은 없었어."
    },
    {
      "scriptJP": "何故か軍が解散しちまって、最近は父ちゃんの仕事の手伝いしてたんだけど。",
      "scriptKO": "왜 인지, 군이 해산되어 버리고, 최근에는 아버지의 일을 돕고 있었지만."
    },
    {
      "scriptJP": "腕は、鈍っちゃいねえぞ！",
      "scriptKO": "실력은, 녹슬지 않았어!"
    },
    {
      "scriptJP": "ブレンダ：頼もしいわね。",
      "scriptKO": "브렌다 : 듬직하군."
    },
    {
      "text": ""
    },
    {
      "text": "[사카타를 동료로 얻었을 때]"
    },
    {
      "text": ""
    },
    {
      "scriptJP": "サカタ：ほほお・・・",
      "scriptKO": "사카타 : 호오..."
    },
    {
      "scriptJP": "中々、頼もしいではないか。",
      "scriptKO": "꽤나, 듬직하지 않은가."
    },
    {
      "text": ""
    },
    {
      "scriptJP": "アクセル：しかし・・・ひでえ奴らだぜ。",
      "scriptKO": "엑셀 : 하지만... 지독한 녀석들이구만."
    },
    {
      "scriptJP": "兵士でもねえ、村の人達を殺すなんてよお。",
      "scriptKO": "병사도 아닌, 마을 사람들을 죽이다니."
    },
    {
      "scriptJP": "クラーク：自分の国でも、同じような事がありました。",
      "scriptKO": "클라크 : 내 나라에서도 같은 일이 있었습니다."
    },
    {
      "scriptJP": "やはり、ソサエティが関わっていたのでしょう。",
      "scriptKO": "역시나, 소사이어티가 관여했을 겁니다."
    },
    {
      "scriptJP": "アルベルト：奴ら、副首相や将軍まで裏で操れる程、",
      "scriptKO": "알베르트 : 녀석들 부 수상이나 장군까지 뒤에서 조종할 정도로,"
    },
    {
      "scriptJP": "力を持っているらしいな。",
      "scriptKO": "힘을 가지고 있는 것 같군."
    },
    {
      "scriptJP": "アクセル：くそお・・・許せねえ！",
      "scriptKO": "엑셀 : 제길.... 용서 못해!"
    },
    {
      "scriptJP": "村の仇は必ず取ってやるぜ！",
      "scriptKO": "반드시 마을의 원수를 갚겠어!"
    }
  ]
}
